{
  "version": "1.1.0",
  "flags": {},
  "shapes": [
    {
      "label": "circle",
      "text": "",
      "points": [
        [
          828.5355121067462,
          510.40346115382636
        ],
        [
          829.4590519949197,
          544.2542837721675
        ],
        [
          801.8717144557538,
          545.0069392367977
        ],
        [
          800.9481745675803,
          511.1561166184566
        ]
      ],
      "group_id": null,
      "shape_type": "rotation",
      "flags": {},
      "direction": 1.543520450592041
    },
    {
      "label": "circle",
      "text": "",
      "points": [
        [
          820.4348969088886,
          765.6435288899125
        ],
        [
          814.8090789720055,
          793.5531016291523
        ],
        [
          792.4393706692355,
          789.0439711100875
        ],
        [
          798.0651886061186,
          761.1343983708477
        ]
      ],
      "group_id": null,
      "shape_type": "rotation",
      "flags": {},
      "direction": 1.769703984260559
    },
    {
      "label": "circle",
      "text": "",
      "points": [
        [
          769.0552501424504,
          510.3655442390813
        ],
        [
          770.2116402150527,
          539.5799770075629
        ],
        [
          745.8292713419255,
          540.5451002921686
        ],
        [
          744.6728812693232,
          511.3306675236871
        ]
      ],
      "group_id": null,
      "shape_type": "rotation",
      "flags": {},
      "direction": 1.5312341451644897
    },
    {
      "label": "circle",
      "text": "",
      "points": [
        [
          776.6819374053322,
          9.97405195067305
        ],
        [
          787.6455188921034,
          37.54950638219171
        ],
        [
          765.874092868106,
          46.20549440552895
        ],
        [
          754.9105113813348,
          18.630039974010288
        ]
      ],
      "group_id": null,
      "shape_type": "rotation",
      "flags": {},
      "direction": 1.1923737525939941
    },
    {
      "label": "circle",
      "text": "",
      "points": [
        [
          774.2176891459111,
          251.17559274160638
        ],
        [
          781.4856162537664,
          285.0927949138196
        ],
        [
          753.2439807759648,
          291.1445366529257
        ],
        [
          745.9760536681096,
          257.22733448071244
        ]
      ],
      "group_id": null,
      "shape_type": "rotation",
      "flags": {},
      "direction": 1.3597042560577393
    },
    {
      "label": "circle",
      "text": "",
      "points": [
        [
          911.042825062776,
          756.3430665881575
        ],
        [
          905.8329434652273,
          783.0070418752348
        ],
        [
          884.7812716169115,
          778.8937498180925
        ],
        [
          889.9911532144602,
          752.2297745310152
        ]
      ],
      "group_id": null,
      "shape_type": "rotation",
      "flags": {},
      "direction": 1.7637555599212646
    },
    {
      "label": "circle",
      "text": "",
      "points": [
        [
          832.7119788926595,
          262.0157721020849
        ],
        [
          839.1656546358515,
          295.26548152612645
        ],
        [
          812.4667320448405,
          300.4476678393211
        ],
        [
          806.0130563016485,
          267.1979584152796
        ]
      ],
      "group_id": null,
      "shape_type": "rotation",
      "flags": {},
      "direction": 1.3790829181671143
    },
    {
      "label": "circle",
      "text": "",
      "points": [
        [
          659.7158274035152,
          853.6095446131274
        ],
        [
          648.4169313802915,
          882.0823273937322
        ],
        [
          623.6984792371098,
          872.2732678868726
        ],
        [
          634.9973752603335,
          843.8004851062678
        ]
      ],
      "group_id": null,
      "shape_type": "rotation",
      "flags": {},
      "direction": 1.9485682249069214
    },
    {
      "label": "circle",
      "text": "",
      "points": [
        [
          834.0656693447005,
          25.99867348509262
        ],
        [
          842.1888696133643,
          53.4719814961623
        ],
        [
          821.1917769443615,
          59.68031974000537
        ],
        [
          813.0685766756977,
          32.2070117289357
        ]
      ],
      "group_id": null,
      "shape_type": "rotation",
      "flags": {},
      "direction": 1.283311128616333
    },
    {
      "label": "circle",
      "text": "",
      "points": [
        [
          763.9334432019444,
          769.1352342739376
        ],
        [
          757.1864581667545,
          797.4443160522637
        ],
        [
          733.5810831652435,
          791.8183790073124
        ],
        [
          740.3280682004334,
          763.5092972289863
        ]
      ],
      "group_id": null,
      "shape_type": "rotation",
      "flags": {},
      "direction": 1.8047643899917603
    }
  ],
  "imagePath": "File30_00002611.bmp",
  "imageData": null,
  "imageHeight": 1024,
  "imageWidth": 1280
}