{
  "version": "1.1.0",
  "flags": {},
  "shapes": [
    {
      "label": "circle",
      "text": "",
      "points": [
        [
          818.7639446012971,
          765.5671575828338
        ],
        [
          812.9348352818548,
          793.4797332657167
        ],
        [
          790.4449177033908,
          788.7830621437282
        ],
        [
          796.2740270228331,
          760.8704864608453
        ]
      ],
      "group_id": null,
      "shape_type": "rotation",
      "flags": {},
      "direction": 1.7766720056533813
    },
    {
      "label": "circle",
      "text": "",
      "points": [
        [
          827.3803845130085,
          510.4359627652909
        ],
        [
          828.0942736305882,
          543.7878661782486
        ],
        [
          800.8946399010536,
          544.370067508147
        ],
        [
          800.1807507834739,
          511.0181640951894
        ]
      ],
      "group_id": null,
      "shape_type": "rotation",
      "flags": {},
      "direction": 1.5493948459625244
    },
    {
      "label": "circle",
      "text": "",
      "points": [
        [
          909.6971817775849,
          756.5304321741971
        ],
        [
          904.4676529790012,
          783.1689662778571
        ],
        [
          882.9788436130401,
          778.9504027867404
        ],
        [
          888.2083724116238,
          752.3118686830804
        ]
      ],
      "group_id": null,
      "shape_type": "rotation",
      "flags": {},
      "direction": 1.7646455764770508
    },
    {
      "label": "circle",
      "text": "",
      "points": [
        [
          767.9672278993858,
          510.75881515500527
        ],
        [
          768.7108549444863,
          539.4187709395295
        ],
        [
          744.7535972959263,
          540.0403791809326
        ],
        [
          744.0099702508257,
          511.38042339640845
        ]
      ],
      "group_id": null,
      "shape_type": "rotation",
      "flags": {},
      "direction": 1.5448555946350098
    },
    {
      "label": "circle",
      "text": "",
      "points": [
        [
          777.9609936833727,
          10.460728979268197
        ],
        [
          788.2706797760998,
          38.19384575188349
        ],
        [
          766.2892504572513,
          46.36536278708979
        ],
        [
          755.9795643645243,
          18.632246014474514
        ]
      ],
      "group_id": null,
      "shape_type": "rotation",
      "flags": {},
      "direction": 1.214881181716919
    },
    {
      "label": "circle",
      "text": "",
      "points": [
        [
          773.7962726555867,
          251.25455301845443
        ],
        [
          781.4259830396667,
          284.43742815472007
        ],
        [
          753.5560222662892,
          290.84554463779557
        ],
        [
          745.9263118822092,
          257.66266950152993
        ]
      ],
      "group_id": null,
      "shape_type": "rotation",
      "flags": {},
      "direction": 1.3447952270507812
    },
    {
      "label": "circle",
      "text": "",
      "points": [
        [
          761.7922784983,
          768.7445362199143
        ],
        [
          755.6551338674483,
          797.2539985603671
        ],
        [
          731.828204900138,
          792.1248485457096
        ],
        [
          737.9653495309897,
          763.6153862052568
        ]
      ],
      "group_id": null,
      "shape_type": "rotation",
      "flags": {},
      "direction": 1.782827615737915
    },
    {
      "label": "circle",
      "text": "",
      "points": [
        [
          832.8265704441121,
          262.2630240667079
        ],
        [
          838.7991597076672,
          294.85046140560314
        ],
        [
          812.2990399074499,
          299.70737388251007
        ],
        [
          806.3264506438949,
          267.1199365436148
        ]
      ],
      "group_id": null,
      "shape_type": "rotation",
      "flags": {},
      "direction": 1.3895292282104492
    },
    {
      "label": "circle",
      "text": "",
      "points": [
        [
          834.8317465182189,
          26.171498462438457
        ],
        [
          842.9766027367043,
          53.67701883090942
        ],
        [
          822.1014810208432,
          59.85850031685754
        ],
        [
          813.9566248023577,
          32.352979948386576
        ]
      ],
      "group_id": null,
      "shape_type": "rotation",
      "flags": {},
      "direction": 1.2829055786132812
    },
    {
      "label": "circle",
      "text": "",
      "points": [
        [
          656.9116905398018,
          852.4048548646294
        ],
        [
          648.4038103196051,
          881.2826048650447
        ],
        [
          621.9888221555107,
          873.5002965025581
        ],
        [
          630.4967023757074,
          844.6225465021428
        ]
      ],
      "group_id": null,
      "shape_type": "rotation",
      "flags": {},
      "direction": 1.8573074340820312
    }
  ],
  "imagePath": "File30_00005370.bmp",
  "imageData": null,
  "imageHeight": 1024,
  "imageWidth": 1280
}