{
  "version": "1.1.0",
  "flags": {},
  "shapes": [
    {
      "label": "circle",
      "text": "",
      "points": [
        [
          828.6322046757915,
          510.40576415373886
        ],
        [
          829.5648577693638,
          544.254631095322
        ],
        [
          801.9815648554585,
          545.0146460025112
        ],
        [
          801.0489117618862,
          511.16577906092795
        ]
      ],
      "group_id": null,
      "shape_type": "rotation",
      "flags": {},
      "direction": 1.5432498455047607
    },
    {
      "label": "circle",
      "text": "",
      "points": [
        [
          820.5113684614812,
          765.5854049590226
        ],
        [
          814.9685668753391,
          793.523106497448
        ],
        [
          792.5878747025808,
          789.0828079316015
        ],
        [
          798.130676288723,
          761.1451063931761
        ]
      ],
      "group_id": null,
      "shape_type": "rotation",
      "flags": {},
      "direction": 1.7666516304016113
    },
    {
      "label": "circle",
      "text": "",
      "points": [
        [
          769.1336069500865,
          510.3453094531115
        ],
        [
          770.3463851712868,
          539.56912919071
        ],
        [
          745.9823598467894,
          540.5802276562644
        ],
        [
          744.7695816255891,
          511.35640791866587
        ]
      ],
      "group_id": null,
      "shape_type": "rotation",
      "flags": {},
      "direction": 1.529320478439331
    },
    {
      "label": "circle",
      "text": "",
      "points": [
        [
          776.9085851366871,
          10.056058531956225
        ],
        [
          787.7517934222537,
          37.676854812942615
        ],
        [
          765.9380945508129,
          46.240347260279776
        ],
        [
          755.0948862652463,
          18.619550979293386
        ]
      ],
      "group_id": null,
      "shape_type": "rotation",
      "flags": {},
      "direction": 1.1967079639434814
    },
    {
      "label": "circle",
      "text": "",
      "points": [
        [
          774.4295454757853,
          251.22520109574853
        ],
        [
          781.6556385631252,
          285.1384774796065
        ],
        [
          753.4237260085906,
          291.1540103300335
        ],
        [
          746.1976329212507,
          257.24073394617557
        ]
      ],
      "group_id": null,
      "shape_type": "rotation",
      "flags": {},
      "direction": 1.3608602285385132
    },
    {
      "label": "circle",
      "text": "",
      "points": [
        [
          911.1680903823028,
          756.343306048698
        ],
        [
          905.9582456403529,
          783.0090181750259
        ],
        [
          884.8974613755097,
          778.894242779427
        ],
        [
          890.1073061174596,
          752.2285306530991
        ]
      ],
      "group_id": null,
      "shape_type": "rotation",
      "flags": {},
      "direction": 1.7637419700622559
    },
    {
      "label": "circle",
      "text": "",
      "points": [
        [
          832.8910396378014,
          262.051002525469
        ],
        [
          839.3256512891994,
          295.3126242732216
        ],
        [
          812.6593754012606,
          300.47133634171894
        ],
        [
          806.2247637498626,
          267.20971459396634
        ]
      ],
      "group_id": null,
      "shape_type": "rotation",
      "flags": {},
      "direction": 1.3797023296356201
    },
    {
      "label": "circle",
      "text": "",
      "points": [
        [
          659.8352409800417,
          853.6159624457031
        ],
        [
          648.5238324363211,
          882.04203492442
        ],
        [
          623.8368781605833,
          872.2185102105469
        ],
        [
          635.1482867043039,
          843.79243773183
        ]
      ],
      "group_id": null,
      "shape_type": "rotation",
      "flags": {},
      "direction": 1.9495115280151367
    },
    {
      "label": "circle",
      "text": "",
      "points": [
        [
          834.2551685859501,
          26.013422141377127
        ],
        [
          842.3118740667678,
          53.53971291297075
        ],
        [
          821.3277171562379,
          59.68159281223688
        ],
        [
          813.2710116754201,
          32.15530204064326
        ]
      ],
      "group_id": null,
      "shape_type": "rotation",
      "flags": {},
      "direction": 1.2860581874847412
    },
    {
      "label": "circle",
      "text": "",
      "points": [
        [
          764.0165381119346,
          769.0896509544509
        ],
        [
          757.3462297622553,
          797.4109700755804
        ],
        [
          733.7258935286895,
          791.8478490455491
        ],
        [
          740.3962018783687,
          763.5265299244196
        ]
      ],
      "group_id": null,
      "shape_type": "rotation",
      "flags": {},
      "direction": 1.8021034002304077
    }
  ],
  "imagePath": "File30_00002665.bmp",
  "imageData": null,
  "imageHeight": 1024,
  "imageWidth": 1280
}