{
  "version": "1.1.0",
  "flags": {},
  "shapes": [
    {
      "label": "circle",
      "text": "",
      "points": [
        [
          827.7080112721129,
          510.5895453416181
        ],
        [
          828.5270285913825,
          544.5079765339185
        ],
        [
          801.080929157575,
          545.1707085646319
        ],
        [
          800.2619118383054,
          511.2522773723315
        ]
      ],
      "group_id": null,
      "shape_type": "rotation",
      "flags": {},
      "direction": 1.5466543436050415
    },
    {
      "label": "circle",
      "text": "",
      "points": [
        [
          768.2125901575519,
          510.1783223270178
        ],
        [
          769.4038921840207,
          539.3205975087441
        ],
        [
          745.1239576940102,
          540.3131327511063
        ],
        [
          743.9326556675413,
          511.17085756937996
        ]
      ],
      "group_id": null,
      "shape_type": "rotation",
      "flags": {},
      "direction": 1.5299402475357056
    },
    {
      "label": "circle",
      "text": "",
      "points": [
        [
          820.4477882249513,
          765.7121616546359
        ],
        [
          814.9134281910714,
          793.6685033733054
        ],
        [
          792.5690574781728,
          789.2451137359882
        ],
        [
          798.1034175120527,
          761.2887720173187
        ]
      ],
      "group_id": null,
      "shape_type": "rotation",
      "flags": {},
      "direction": 1.7662338018417358
    },
    {
      "label": "circle",
      "text": "",
      "points": [
        [
          772.5337215569645,
          250.48942747951426
        ],
        [
          780.0373898463964,
          284.53961388621883
        ],
        [
          751.5993350836596,
          290.8065319931418
        ],
        [
          744.0956667942277,
          256.7563455864372
        ]
      ],
      "group_id": null,
      "shape_type": "rotation",
      "flags": {},
      "direction": 1.3538923263549805
    },
    {
      "label": "circle",
      "text": "",
      "points": [
        [
          911.146827258891,
          756.2690773571998
        ],
        [
          905.9316850844164,
          782.9685162578818
        ],
        [
          884.861229381734,
          778.8528708849877
        ],
        [
          890.0763715562086,
          752.1534319843057
        ]
      ],
      "group_id": null,
      "shape_type": "rotation",
      "flags": {},
      "direction": 1.7636953592300415
    },
    {
      "label": "circle",
      "text": "",
      "points": [
        [
          659.7440252781156,
          853.4294697005739
        ],
        [
          648.8870170969641,
          881.9750493200511
        ],
        [
          624.1013116359469,
          872.5480693619261
        ],
        [
          634.9583198170984,
          844.0024897424489
        ]
      ],
      "group_id": null,
      "shape_type": "rotation",
      "flags": {},
      "direction": 1.9342398643493652
    },
    {
      "label": "circle",
      "text": "",
      "points": [
        [
          831.3460281259544,
          261.8492438385276
        ],
        [
          837.4433796208693,
          295.25757808782515
        ],
        [
          810.6526291006077,
          300.1471550872544
        ],
        [
          804.5552776056927,
          266.7388208379569
        ]
      ],
      "group_id": null,
      "shape_type": "rotation",
      "flags": {},
      "direction": 1.3902733325958252
    },
    {
      "label": "circle",
      "text": "",
      "points": [
        [
          774.3192727652851,
          8.988518257259173
        ],
        [
          784.9049266325849,
          36.660053196035236
        ],
        [
          762.9235250862772,
          45.06896541583683
        ],
        [
          752.3378712189774,
          17.397430477060766
        ]
      ],
      "group_id": null,
      "shape_type": "rotation",
      "flags": {},
      "direction": 1.2054258584976196
    },
    {
      "label": "circle",
      "text": "",
      "points": [
        [
          831.8881505880634,
          25.48287962081646
        ],
        [
          839.5859532542089,
          52.87942843132493
        ],
        [
          818.3447595681866,
          58.84771730301154
        ],
        [
          810.6469569020411,
          31.451168492503065
        ]
      ],
      "group_id": null,
      "shape_type": "rotation",
      "flags": {},
      "direction": 1.2968817949295044
    },
    {
      "label": "circle",
      "text": "",
      "points": [
        [
          763.9160486514247,
          769.0068898601969
        ],
        [
          757.3805695250379,
          797.3989714989247
        ],
        [
          733.7489904110753,
          791.959296663241
        ],
        [
          740.2844695374621,
          763.5672150245133
        ]
      ],
      "group_id": null,
      "shape_type": "rotation",
      "flags": {},
      "direction": 1.7970420122146606
    }
  ],
  "imagePath": "File30_00005748.bmp",
  "imageData": null,
  "imageHeight": 1024,
  "imageWidth": 1280
}