{
  "version": "1.1.0",
  "flags": {},
  "shapes": [
    {
      "label": "circle",
      "text": "",
      "points": [
        [
          779.54867053895,
          10.794210109127206
        ],
        [
          790.1510422737348,
          38.422254890161796
        ],
        [
          768.237828484488,
          46.8315375715368
        ],
        [
          757.6354567497032,
          19.203492790502207
        ]
      ],
      "group_id": null,
      "shape_type": "rotation",
      "flags": {},
      "direction": 1.2043731212615967
    },
    {
      "label": "circle",
      "text": "",
      "points": [
        [
          829.7229869287057,
          510.2508110125067
        ],
        [
          830.8504785688218,
          544.0115148404516
        ],
        [
          803.1185658056702,
          544.9376655499933
        ],
        [
          801.9910741655541,
          511.1769617220484
        ]
      ],
      "group_id": null,
      "shape_type": "rotation",
      "flags": {},
      "direction": 1.537412166595459
    },
    {
      "label": "circle",
      "text": "",
      "points": [
        [
          821.2257834601334,
          765.4243744545249
        ],
        [
          815.49737084159,
          793.4270542009026
        ],
        [
          793.1744850945546,
          788.860537654851
        ],
        [
          798.9028977130979,
          760.8578579084733
        ]
      ],
      "group_id": null,
      "shape_type": "rotation",
      "flags": {},
      "direction": 1.7725789546966553
    },
    {
      "label": "circle",
      "text": "",
      "points": [
        [
          776.7006541624955,
          251.72781231126794
        ],
        [
          783.2247505054478,
          285.6354283202976
        ],
        [
          754.8078907593804,
          291.1030592707641
        ],
        [
          748.2837944164281,
          257.19544326173445
        ]
      ],
      "group_id": null,
      "shape_type": "rotation",
      "flags": {},
      "direction": 1.380711317062378
    },
    {
      "label": "circle",
      "text": "",
      "points": [
        [
          770.3454142672343,
          510.4511398687114
        ],
        [
          771.4515481720214,
          539.6697270106404
        ],
        [
          747.1941365140157,
          540.5880447016007
        ],
        [
          746.0880026092286,
          511.3694575596717
        ]
      ],
      "group_id": null,
      "shape_type": "rotation",
      "flags": {},
      "direction": 1.5329571962356567
    },
    {
      "label": "circle",
      "text": "",
      "points": [
        [
          660.8918777912348,
          853.8487760139698
        ],
        [
          648.5322821140969,
          882.2067231613889
        ],
        [
          623.9142745525152,
          871.4771517204052
        ],
        [
          636.2738702296531,
          843.1192045729861
        ]
      ],
      "group_id": null,
      "shape_type": "rotation",
      "flags": {},
      "direction": 1.9818146228790283
    },
    {
      "label": "circle",
      "text": "",
      "points": [
        [
          834.8082538713865,
          262.22079345562685
        ],
        [
          840.9401843738808,
          295.6124737260011
        ],
        [
          814.2071269879895,
          300.52163818499713
        ],
        [
          808.0751964854951,
          267.1299579146229
        ]
      ],
      "group_id": null,
      "shape_type": "rotation",
      "flags": {},
      "direction": 1.3891832828521729
    },
    {
      "label": "circle",
      "text": "",
      "points": [
        [
          911.7915891379349,
          756.1602203001412
        ],
        [
          906.8624728838611,
          783.1771538464876
        ],
        [
          885.8214479714401,
          779.3383148561088
        ],
        [
          890.7505642255139,
          752.3213813097624
        ]
      ],
      "group_id": null,
      "shape_type": "rotation",
      "flags": {},
      "direction": 1.7512569427490234
    },
    {
      "label": "circle",
      "text": "",
      "points": [
        [
          764.6896895772538,
          768.9647523848836
        ],
        [
          757.9804695918043,
          797.3118666398743
        ],
        [
          734.3674393289962,
          791.7231138260544
        ],
        [
          741.0766593144457,
          763.3759995710636
        ]
      ],
      "group_id": null,
      "shape_type": "rotation",
      "flags": {},
      "direction": 1.803200602531433
    },
    {
      "label": "circle",
      "text": "",
      "points": [
        [
          836.73964181484,
          26.763777036704973
        ],
        [
          844.6958209607104,
          54.12569208919641
        ],
        [
          823.597638458598,
          60.26053021427102
        ],
        [
          815.6414593127275,
          32.89861516177958
        ]
      ],
      "group_id": null,
      "shape_type": "rotation",
      "flags": {},
      "direction": 1.2878235578536987
    }
  ],
  "imagePath": "File30_00005505.bmp",
  "imageData": null,
  "imageHeight": 1024,
  "imageWidth": 1280
}