{
  "version": "1.1.0",
  "flags": {},
  "shapes": [
    {
      "label": "circle",
      "text": "",
      "points": [
        [
          818.6055294677924,
          765.668508371777
        ],
        [
          812.9698345649479,
          793.6167087940489
        ],
        [
          790.4336551025197,
          789.0723363547851
        ],
        [
          796.0693500053642,
          761.1241359325131
        ]
      ],
      "group_id": null,
      "shape_type": "rotation",
      "flags": {},
      "direction": 1.7697758674621582
    },
    {
      "label": "circle",
      "text": "",
      "points": [
        [
          767.5449557561237,
          510.27738989017973
        ],
        [
          768.5831815161501,
          539.5527098129077
        ],
        [
          743.8525051813763,
          540.4297634301323
        ],
        [
          742.8142794213499,
          511.1544435074043
        ]
      ],
      "group_id": null,
      "shape_type": "rotation",
      "flags": {},
      "direction": 1.5353469848632812
    },
    {
      "label": "circle",
      "text": "",
      "points": [
        [
          826.9318863435459,
          510.2526298324002
        ],
        [
          827.6716733549393,
          544.244172304125
        ],
        [
          800.013304086142,
          544.8461250504118
        ],
        [
          799.2735170747486,
          510.85458257868703
        ]
      ],
      "group_id": null,
      "shape_type": "rotation",
      "flags": {},
      "direction": 1.549035906791687
    },
    {
      "label": "circle",
      "text": "",
      "points": [
        [
          909.5784234071589,
          756.4260878881771
        ],
        [
          904.6093154777146,
          783.1178996804064
        ],
        [
          883.1032172178411,
          779.1141953149479
        ],
        [
          888.0723251472854,
          752.4223835227186
        ]
      ],
      "group_id": null,
      "shape_type": "rotation",
      "flags": {},
      "direction": 1.7548552751541138
    },
    {
      "label": "circle",
      "text": "",
      "points": [
        [
          772.8999883046196,
          250.78364913703473
        ],
        [
          780.2740889395817,
          284.7224725233174
        ],
        [
          751.8269404063184,
          290.90336258171527
        ],
        [
          744.4528397713563,
          256.9645391954326
        ]
      ],
      "group_id": null,
      "shape_type": "rotation",
      "flags": {},
      "direction": 1.356845498085022
    },
    {
      "label": "circle",
      "text": "",
      "points": [
        [
          761.5297251527282,
          768.5601733286941
        ],
        [
          755.9947011000124,
          797.1848326833713
        ],
        [
          731.936705511334,
          792.53284424943
        ],
        [
          737.4717295640498,
          763.9081848947528
        ]
      ],
      "group_id": null,
      "shape_type": "rotation",
      "flags": {},
      "direction": 1.7618045806884766
    },
    {
      "label": "circle",
      "text": "",
      "points": [
        [
          831.5234142978056,
          261.7805093682924
        ],
        [
          837.7936774161035,
          295.06276724609677
        ],
        [
          811.0719226162564,
          300.0970541082696
        ],
        [
          804.8016594979586,
          266.8147962304653
        ]
      ],
      "group_id": null,
      "shape_type": "rotation",
      "flags": {},
      "direction": 1.3845824003219604
    },
    {
      "label": "circle",
      "text": "",
      "points": [
        [
          775.4038300755218,
          9.597200495550616
        ],
        [
          786.6341236970537,
          37.14420514549521
        ],
        [
          764.8653349635402,
          46.01885022466338
        ],
        [
          753.6350413420083,
          18.471845574718785
        ]
      ],
      "group_id": null,
      "shape_type": "rotation",
      "flags": {},
      "direction": 1.183688998222351
    },
    {
      "label": "circle",
      "text": "",
      "points": [
        [
          833.1698208429377,
          25.908783482022102
        ],
        [
          841.0217999959123,
          53.421899389545345
        ],
        [
          819.8783969305002,
          59.45602364688389
        ],
        [
          812.0264177775257,
          31.94290773936065
        ]
      ],
      "group_id": null,
      "shape_type": "rotation",
      "flags": {},
      "direction": 1.2927961349487305
    },
    {
      "label": "circle",
      "text": "",
      "points": [
        [
          655.9859520383059,
          851.5799880183873
        ],
        [
          649.7230262898008,
          880.8726367544422
        ],
        [
          622.9442237429441,
          875.1471848331752
        ],
        [
          629.2071494914492,
          845.8545360971203
        ]
      ],
      "group_id": null,
      "shape_type": "rotation",
      "flags": {},
      "direction": 1.7814303636550903
    }
  ],
  "imagePath": "File30_00006378.bmp",
  "imageData": null,
  "imageHeight": 1024,
  "imageWidth": 1280
}